apydia
