Metadata-Version: 1.0
Name: Apydia
Version: 0.0.2
Summary: API Reference Documentation Generator for Python
Home-page: http://apydia.ematia.de
Author: Daniel Haus
Author-email: daniel.haus@ematia.de
License: MIT License
Platform: UNKNOWN
Classifier: Development Status :: 3 - Alpha
Classifier: Environment :: Console
Classifier: Environment :: Web Environment
Classifier: Intended Audience :: Developers
Classifier: License :: OSI Approved :: MIT License
Classifier: Operating System :: OS Independent
Classifier: Programming Language :: Python
Classifier: Topic :: Software Development :: Documentation
Classifier: Topic :: Internet :: WWW/HTTP
